{
  "brand": "Royal Enfield",
  "brandId": "royalenfield",
  "type": "2w",
  "lastUpdated": "2026-04-02",
  "source": "BikeWale",
  "vehicles": [
    {
      "make": "Royal Enfield",
      "model": "Guerrilla 450",
      "variant_name": "Guerrilla 450",
      "price": "N/A",
      "engine_displacement": "N/A cc",
      "mileage": "N/A kmpl",
      "max_power": "N/A bhp",
      "max_torque": "N/A",
      "top_speed": "N/A kmph",
      "fuel_type": "Petrol",
      "source_section": "Discontinued",
      "description": "The Royal Enfield Guerrilla 450 is a two-wheeler available in India.",
      "features": [],
      "variants": [
        {
          "name": "Dash - Twilight Blue",
          "price": "N/A"
        },
        {
          "name": "APEX - Red",
          "price": "N/A"
        },
        {
          "name": "APEX - Black and Green",
          "price": "N/A"
        },
        {
          "name": "Dash - Shadow Ash - Smoke Silver - Peix Bronze",
          "price": "N/A"
        },
        {
          "name": "Flash - Brava Blue",
          "price": "N/A"
        }
      ],
      "colors": [],
      "technical_specifications": {}
    },
    {
      "make": "Royal Enfield",
      "model": "Hunter 350",
      "variant_name": "Hunter 350",
      "price": "N/A",
      "engine_displacement": "N/A cc",
      "mileage": "N/A kmpl",
      "max_power": "N/A bhp",
      "max_torque": "N/A",
      "top_speed": "N/A kmph",
      "fuel_type": "Petrol",
      "source_section": "Discontinued",
      "description": "The Royal Enfield Hunter 350 is a two-wheeler available in India.",
      "features": [],
      "variants": [
        {
          "name": "Standard",
          "price": "N/A"
        },
        {
          "name": "Mid",
          "price": "N/A"
        },
        {
          "name": "Top",
          "price": "N/A"
        }
      ],
      "colors": [],
      "technical_specifications": {}
    },
    {
      "make": "Royal Enfield",
      "model": "Classic 350",
      "variant_name": "Classic 350",
      "price": "N/A",
      "engine_displacement": "N/A cc",
      "mileage": "N/A kmpl",
      "max_power": "N/A bhp",
      "max_torque": "N/A",
      "top_speed": "N/A kmph",
      "fuel_type": "Petrol",
      "source_section": "Discontinued",
      "description": "The Royal Enfield Classic 350 is a two-wheeler available in India.",
      "features": [],
      "variants": [
        {
          "name": "Redditch",
          "price": "N/A"
        },
        {
          "name": "Halcyon",
          "price": "N/A"
        },
        {
          "name": "Heritage",
          "price": "N/A"
        },
        {
          "name": "Heritage Premium",
          "price": "N/A"
        },
        {
          "name": "Signals",
          "price": "N/A"
        },
        {
          "name": "Dark",
          "price": "N/A"
        },
        {
          "name": "Chrome",
          "price": "N/A"
        }
      ],
      "colors": [],
      "technical_specifications": {}
    },
    {
      "make": "Royal Enfield",
      "model": "Bullet 350",
      "variant_name": "Bullet 350",
      "price": "N/A",
      "engine_displacement": "N/A cc",
      "mileage": "N/A kmpl",
      "max_power": "N/A bhp",
      "max_torque": "N/A",
      "top_speed": "N/A kmph",
      "fuel_type": "Petrol",
      "source_section": "Discontinued",
      "description": "The Royal Enfield Bullet 350 is a two-wheeler available in India.",
      "features": [],
      "variants": [
        {
          "name": "Battalion Black",
          "price": "N/A"
        },
        {
          "name": "Base",
          "price": "N/A"
        },
        {
          "name": "Mid",
          "price": "N/A"
        },
        {
          "name": "Top",
          "price": "N/A"
        }
      ],
      "colors": [],
      "technical_specifications": {}
    },
    {
      "make": "Royal Enfield",
      "model": "Continental GT 650",
      "variant_name": "Continental GT 650",
      "price": "N/A",
      "engine_displacement": "N/A cc",
      "mileage": "N/A kmpl",
      "max_power": "N/A bhp",
      "max_torque": "N/A",
      "top_speed": "N/A kmph",
      "fuel_type": "Petrol",
      "source_section": "Discontinued",
      "description": "The Royal Enfield Continental GT 650 is a two-wheeler available in India.",
      "features": [],
      "variants": [
        {
          "name": "Standard",
          "price": "N/A"
        },
        {
          "name": "Alloy Wheel",
          "price": "N/A"
        },
        {
          "name": "Chrome",
          "price": "N/A"
        }
      ],
      "colors": [],
      "technical_specifications": {}
    },
    {
      "make": "Royal Enfield",
      "model": "Meteor 350",
      "variant_name": "Meteor 350",
      "price": "N/A",
      "engine_displacement": "N/A cc",
      "mileage": "N/A kmpl",
      "max_power": "N/A bhp",
      "max_torque": "N/A",
      "top_speed": "N/A kmph",
      "fuel_type": "Petrol",
      "source_section": "Discontinued",
      "description": "The Royal Enfield Meteor 350 is a two-wheeler available in India.",
      "features": [],
      "variants": [
        {
          "name": "Fireball",
          "price": "N/A"
        },
        {
          "name": "Stellar",
          "price": "N/A"
        },
        {
          "name": "Aurora",
          "price": "N/A"
        },
        {
          "name": "Supernova",
          "price": "N/A"
        },
        {
          "name": "Sundowner Orange Special Edition",
          "price": "N/A"
        }
      ],
      "colors": [],
      "technical_specifications": {}
    },
    {
      "make": "Royal Enfield",
      "model": "Himalayan 450",
      "variant_name": "Himalayan 450",
      "price": "N/A",
      "engine_displacement": "N/A cc",
      "mileage": "N/A kmpl",
      "max_power": "N/A bhp",
      "max_torque": "N/A",
      "top_speed": "N/A kmph",
      "fuel_type": "Petrol",
      "source_section": "Discontinued",
      "description": "The Royal Enfield Himalayan 450 is a two-wheeler available in India.",
      "features": [],
      "variants": [
        {
          "name": "Base",
          "price": "N/A"
        },
        {
          "name": "Pass",
          "price": "N/A"
        },
        {
          "name": "Summit",
          "price": "N/A"
        },
        {
          "name": "Hanle Black",
          "price": "N/A"
        },
        {
          "name": "Mana Black",
          "price": "N/A"
        }
      ],
      "colors": [],
      "technical_specifications": {}
    },
    {
      "make": "Royal Enfield",
      "model": "Super Meteor 650",
      "variant_name": "Super Meteor 650",
      "price": "N/A",
      "engine_displacement": "N/A cc",
      "mileage": "N/A kmpl",
      "max_power": "N/A bhp",
      "max_torque": "N/A",
      "top_speed": "N/A kmph",
      "fuel_type": "Petrol",
      "source_section": "Discontinued",
      "description": "The Royal Enfield Super Meteor 650 is a two-wheeler available in India.",
      "features": [],
      "variants": [
        {
          "name": "Astral",
          "price": "N/A"
        },
        {
          "name": "Interstellar",
          "price": "N/A"
        },
        {
          "name": "Celestial",
          "price": "N/A"
        }
      ],
      "colors": [],
      "technical_specifications": {}
    },
    {
      "make": "Royal Enfield",
      "model": "Shotgun 650",
      "variant_name": "Shotgun 650",
      "price": "N/A",
      "engine_displacement": "N/A cc",
      "mileage": "N/A kmpl",
      "max_power": "N/A bhp",
      "max_torque": "N/A",
      "top_speed": "N/A kmph",
      "fuel_type": "Petrol",
      "source_section": "Discontinued",
      "description": "The Royal Enfield Shotgun 650 is a two-wheeler available in India.",
      "features": [],
      "variants": [
        {
          "name": "Custom Shed",
          "price": "N/A"
        },
        {
          "name": "Custom Pro",
          "price": "N/A"
        },
        {
          "name": "Custom Special",
          "price": "N/A"
        },
        {
          "name": "X Rough Crafts",
          "price": "N/A"
        }
      ],
      "colors": [],
      "technical_specifications": {}
    },
    {
      "make": "Royal Enfield",
      "model": "Interceptor 650",
      "variant_name": "Interceptor 650",
      "price": "N/A",
      "engine_displacement": "N/A cc",
      "mileage": "N/A kmpl",
      "max_power": "N/A bhp",
      "max_torque": "N/A",
      "top_speed": "N/A kmph",
      "fuel_type": "Petrol",
      "source_section": "Discontinued",
      "description": "The Royal Enfield Interceptor 650 is a two-wheeler available in India.",
      "features": [],
      "variants": [
        {
          "name": "Standard",
          "price": "N/A"
        },
        {
          "name": "Custom",
          "price": "N/A"
        },
        {
          "name": "Alloy Wheel",
          "price": "N/A"
        },
        {
          "name": "Chrome",
          "price": "N/A"
        }
      ],
      "colors": [],
      "technical_specifications": {}
    },
    {
      "make": "Royal Enfield",
      "model": "Classic 650",
      "variant_name": "Classic 650",
      "price": "N/A",
      "engine_displacement": "N/A cc",
      "mileage": "N/A kmpl",
      "max_power": "N/A bhp",
      "max_torque": "N/A",
      "top_speed": "N/A kmph",
      "fuel_type": "Petrol",
      "source_section": "Discontinued",
      "description": "The Royal Enfield Classic 650 is a two-wheeler available in India.",
      "features": [],
      "variants": [
        {
          "name": "Hotrod",
          "price": "N/A"
        },
        {
          "name": "Classic",
          "price": "N/A"
        },
        {
          "name": "Chrome",
          "price": "N/A"
        },
        {
          "name": "125th Anniversary Edition",
          "price": "N/A"
        }
      ],
      "colors": [],
      "technical_specifications": {}
    },
    {
      "make": "Royal Enfield",
      "model": "Goan Classic 350",
      "variant_name": "Goan Classic 350",
      "price": "N/A",
      "engine_displacement": "N/A cc",
      "mileage": "N/A kmpl",
      "max_power": "N/A bhp",
      "max_torque": "N/A",
      "top_speed": "N/A kmph",
      "fuel_type": "Petrol",
      "source_section": "Discontinued",
      "description": "The Royal Enfield Goan Classic 350 is a two-wheeler available in India.",
      "features": [],
      "variants": [
        {
          "name": "Single Tone",
          "price": "N/A"
        },
        {
          "name": "Dual Tone",
          "price": "N/A"
        }
      ],
      "colors": [],
      "technical_specifications": {}
    },
    {
      "make": "Royal Enfield",
      "model": "Scram 440",
      "variant_name": "Scram 440",
      "price": "N/A",
      "engine_displacement": "N/A cc",
      "mileage": "N/A kmpl",
      "max_power": "N/A bhp",
      "max_torque": "N/A",
      "top_speed": "N/A kmph",
      "fuel_type": "Petrol",
      "source_section": "Discontinued",
      "description": "The Royal Enfield Scram 440 is a two-wheeler available in India.",
      "features": [],
      "variants": [
        {
          "name": "Trail",
          "price": "N/A"
        },
        {
          "name": "Force",
          "price": "N/A"
        }
      ],
      "colors": [],
      "technical_specifications": {}
    },
    {
      "make": "Royal Enfield",
      "model": "Bear 650",
      "variant_name": "Bear 650",
      "price": "N/A",
      "engine_displacement": "N/A cc",
      "mileage": "N/A kmpl",
      "max_power": "N/A bhp",
      "max_torque": "N/A",
      "top_speed": "N/A kmph",
      "fuel_type": "Petrol",
      "source_section": "Discontinued",
      "description": "The Royal Enfield Bear 650 is a two-wheeler available in India.",
      "features": [],
      "variants": [
        {
          "name": "Broadwalk White",
          "price": "N/A"
        },
        {
          "name": "Petrol Green and Wild Honey",
          "price": "N/A"
        },
        {
          "name": "Golden Shadow",
          "price": "N/A"
        },
        {
          "name": "Two Four Nine",
          "price": "N/A"
        }
      ],
      "colors": [],
      "technical_specifications": {}
    },
    {
      "make": "Royal Enfield",
      "model": "Flying Flea C6",
      "variant_name": "Flying Flea C6",
      "price": "N/A",
      "engine_displacement": "N/A cc",
      "mileage": "N/A kmpl",
      "max_power": "N/A bhp",
      "max_torque": "N/A",
      "top_speed": "N/A kmph",
      "fuel_type": "Petrol",
      "source_section": "Available",
      "description": "The Royal Enfield Flying Flea C6 is a two-wheeler available in India.",
      "features": [],
      "variants": [
        {
          "name": "Standard",
          "price": "N/A"
        }
      ],
      "colors": [],
      "technical_specifications": {}
    },
    {
      "make": "Royal Enfield",
      "model": "Bullet 650",
      "variant_name": "Bullet 650",
      "price": "N/A",
      "engine_displacement": "N/A cc",
      "mileage": "N/A kmpl",
      "max_power": "N/A bhp",
      "max_torque": "N/A",
      "top_speed": "N/A kmph",
      "fuel_type": "Petrol",
      "source_section": "Available",
      "description": "The Royal Enfield Bullet 650 is a two-wheeler available in India.",
      "features": [],
      "variants": [
        {
          "name": "Standard",
          "price": "N/A"
        }
      ],
      "colors": [],
      "technical_specifications": {}
    },
    {
      "make": "Royal Enfield",
      "model": "Continental GT 450",
      "variant_name": "Continental GT 450",
      "price": "N/A",
      "engine_displacement": "N/A cc",
      "mileage": "N/A kmpl",
      "max_power": "N/A bhp",
      "max_torque": "N/A",
      "top_speed": "N/A kmph",
      "fuel_type": "Petrol",
      "source_section": "Available",
      "description": "The Royal Enfield Continental GT 450 is a two-wheeler available in India.",
      "features": [],
      "variants": [
        {
          "name": "Standard",
          "price": "N/A"
        }
      ],
      "colors": [],
      "technical_specifications": {}
    },
    {
      "make": "Royal Enfield",
      "model": "Scrambler 450",
      "variant_name": "Scrambler 450",
      "price": "N/A",
      "engine_displacement": "N/A cc",
      "mileage": "N/A kmpl",
      "max_power": "N/A bhp",
      "max_torque": "N/A",
      "top_speed": "N/A kmph",
      "fuel_type": "Petrol",
      "source_section": "Available",
      "description": "The Royal Enfield Scrambler 450 is a two-wheeler available in India.",
      "features": [],
      "variants": [
        {
          "name": "Standard",
          "price": "N/A"
        }
      ],
      "colors": [],
      "technical_specifications": {}
    },
    {
      "make": "Royal Enfield",
      "model": "Continental GT 750",
      "variant_name": "Continental GT 750",
      "price": "N/A",
      "engine_displacement": "N/A cc",
      "mileage": "N/A kmpl",
      "max_power": "N/A bhp",
      "max_torque": "N/A",
      "top_speed": "N/A kmph",
      "fuel_type": "Petrol",
      "source_section": "Available",
      "description": "The Royal Enfield Continental GT 750 is a two-wheeler available in India.",
      "features": [],
      "variants": [
        {
          "name": "Standard",
          "price": "N/A"
        }
      ],
      "colors": [],
      "technical_specifications": {}
    },
    {
      "make": "Royal Enfield",
      "model": "Himalayan 750",
      "variant_name": "Himalayan 750",
      "price": "N/A",
      "engine_displacement": "N/A cc",
      "mileage": "N/A kmpl",
      "max_power": "N/A bhp",
      "max_torque": "N/A",
      "top_speed": "N/A kmph",
      "fuel_type": "Petrol",
      "source_section": "Available",
      "description": "The Royal Enfield Himalayan 750 is a two-wheeler available in India.",
      "features": [],
      "variants": [
        {
          "name": "Standard",
          "price": "N/A"
        }
      ],
      "colors": [],
      "technical_specifications": {}
    },
    {
      "make": "Royal Enfield",
      "model": "Himalayan Electric",
      "variant_name": "Himalayan Electric",
      "price": "N/A",
      "engine_displacement": "N/A cc",
      "mileage": "N/A kmpl",
      "max_power": "N/A bhp",
      "max_torque": "N/A",
      "top_speed": "N/A kmph",
      "fuel_type": "Petrol",
      "source_section": "Available",
      "description": "The Royal Enfield Himalayan Electric is a two-wheeler available in India.",
      "features": [],
      "variants": [
        {
          "name": "Standard",
          "price": "N/A"
        }
      ],
      "colors": [],
      "technical_specifications": {}
    },
    {
      "make": "Royal Enfield",
      "model": "Flying Flea S6 Scrambler",
      "variant_name": "Flying Flea S6 Scrambler",
      "price": "N/A",
      "engine_displacement": "N/A cc",
      "mileage": "N/A kmpl",
      "max_power": "N/A bhp",
      "max_torque": "N/A",
      "top_speed": "N/A kmph",
      "fuel_type": "Petrol",
      "source_section": "Available",
      "description": "The Royal Enfield Flying Flea S6 Scrambler is a two-wheeler available in India.",
      "features": [],
      "variants": [
        {
          "name": "Standard",
          "price": "N/A"
        }
      ],
      "colors": [],
      "technical_specifications": {}
    },
    {
      "make": "Royal Enfield",
      "model": "Himalayan Raid 450",
      "variant_name": "Himalayan Raid 450",
      "price": "N/A",
      "engine_displacement": "N/A cc",
      "mileage": "N/A kmpl",
      "max_power": "N/A bhp",
      "max_torque": "N/A",
      "top_speed": "N/A kmph",
      "fuel_type": "Petrol",
      "source_section": "Available",
      "description": "The Royal Enfield Himalayan Raid 450 is a two-wheeler available in India.",
      "features": [],
      "variants": [
        {
          "name": "Standard",
          "price": "N/A"
        }
      ],
      "colors": [],
      "technical_specifications": {}
    },
    {
      "make": "Royal Enfield",
      "model": "Meteor 350 [2024]",
      "variant_name": "Meteor 350 [2024]",
      "price": "N/A",
      "engine_displacement": "N/A cc",
      "mileage": "N/A kmpl",
      "max_power": "N/A bhp",
      "max_torque": "N/A",
      "top_speed": "N/A kmph",
      "fuel_type": "Petrol",
      "source_section": "Available",
      "description": "The Royal Enfield Meteor 350 [2024] is a two-wheeler available in India.",
      "features": [],
      "variants": [
        {
          "name": "Fireball",
          "price": "N/A"
        },
        {
          "name": "Stellar",
          "price": "N/A"
        },
        {
          "name": "Supernova",
          "price": "N/A"
        },
        {
          "name": "Aurora",
          "price": "N/A"
        }
      ],
      "colors": [],
      "technical_specifications": {}
    },
    {
      "make": "Royal Enfield",
      "model": "Guerrilla 450 [2024-2026]",
      "variant_name": "Guerrilla 450 [2024-2026]",
      "price": "N/A",
      "engine_displacement": "N/A cc",
      "mileage": "N/A kmpl",
      "max_power": "N/A bhp",
      "max_torque": "N/A",
      "top_speed": "N/A kmph",
      "fuel_type": "Petrol",
      "source_section": "Available",
      "description": "The Royal Enfield Guerrilla 450 [2024-2026] is a two-wheeler available in India.",
      "features": [],
      "variants": [
        {
          "name": "Flash",
          "price": "N/A"
        },
        {
          "name": "Dash",
          "price": "N/A"
        },
        {
          "name": "Analogue",
          "price": "N/A"
        }
      ],
      "colors": [],
      "technical_specifications": {}
    },
    {
      "make": "Royal Enfield",
      "model": "Scram 411",
      "variant_name": "Scram 411",
      "price": "N/A",
      "engine_displacement": "N/A cc",
      "mileage": "N/A kmpl",
      "max_power": "N/A bhp",
      "max_torque": "N/A",
      "top_speed": "N/A kmph",
      "fuel_type": "Petrol",
      "source_section": "Available",
      "description": "The Royal Enfield Scram 411 is a two-wheeler available in India.",
      "features": [],
      "variants": [
        {
          "name": "Graphite Blue - Graphite Red - Graphite Yellow",
          "price": "N/A"
        },
        {
          "name": "Blazing Black and Skyline Blue",
          "price": "N/A"
        },
        {
          "name": "White Flame and Silver Spirit",
          "price": "N/A"
        }
      ],
      "colors": [],
      "technical_specifications": {}
    },
    {
      "make": "Royal Enfield",
      "model": "Thunderbird 350",
      "variant_name": "Thunderbird 350",
      "price": "N/A",
      "engine_displacement": "N/A cc",
      "mileage": "N/A kmpl",
      "max_power": "N/A bhp",
      "max_torque": "N/A",
      "top_speed": "N/A kmph",
      "fuel_type": "Petrol",
      "source_section": "Available",
      "description": "The Royal Enfield Thunderbird 350 is a two-wheeler available in India.",
      "features": [],
      "variants": [
        {
          "name": "Standard",
          "price": "N/A"
        },
        {
          "name": "Disc",
          "price": "N/A"
        },
        {
          "name": "Disc Self",
          "price": "N/A"
        },
        {
          "name": "ABS",
          "price": "N/A"
        }
      ],
      "colors": [],
      "technical_specifications": {}
    },
    {
      "make": "Royal Enfield",
      "model": "Himalayan [2015-2023]",
      "variant_name": "Himalayan [2015-2023]",
      "price": "N/A",
      "engine_displacement": "N/A cc",
      "mileage": "N/A kmpl",
      "max_power": "N/A bhp",
      "max_torque": "N/A",
      "top_speed": "N/A kmph",
      "fuel_type": "Petrol",
      "source_section": "Available",
      "description": "The Royal Enfield Himalayan [2015-2023] is a two-wheeler available in India.",
      "features": [],
      "variants": [
        {
          "name": "Carburetor",
          "price": "N/A"
        },
        {
          "name": "Fi",
          "price": "N/A"
        },
        {
          "name": "Sleet",
          "price": "N/A"
        },
        {
          "name": "Fi ABS - BS IV",
          "price": "N/A"
        },
        {
          "name": "Sleet ABS - BS IV",
          "price": "N/A"
        },
        {
          "name": "Standard - BS VI [2020]",
          "price": "N/A"
        },
        {
          "name": "Sleet and Gravel Grey [2020]",
          "price": "N/A"
        },
        {
          "name": "Dual Tone - BS VI [2020]",
          "price": "N/A"
        },
        {
          "name": "Standard",
          "price": "N/A"
        },
        {
          "name": "Dual Tone - BS VI [2021]",
          "price": "N/A"
        },
        {
          "name": "Pine Green and Granite Black [2021]",
          "price": "N/A"
        },
        {
          "name": "Pine Green and Dune Brown",
          "price": "N/A"
        },
        {
          "name": "Glacier Blue and Granite Black",
          "price": "N/A"
        },
        {
          "name": "Sleet Black",
          "price": "N/A"
        }
      ],
      "colors": [],
      "technical_specifications": {}
    },
    {
      "make": "Royal Enfield",
      "model": "Classic Signals",
      "variant_name": "Classic Signals",
      "price": "N/A",
      "engine_displacement": "N/A cc",
      "mileage": "N/A kmpl",
      "max_power": "N/A bhp",
      "max_torque": "N/A",
      "top_speed": "N/A kmph",
      "fuel_type": "Petrol",
      "source_section": "Available",
      "description": "The Royal Enfield Classic Signals is a two-wheeler available in India.",
      "features": [],
      "variants": [
        {
          "name": "ABS",
          "price": "N/A"
        }
      ],
      "colors": [],
      "technical_specifications": {}
    },
    {
      "make": "Royal Enfield",
      "model": "Classic Stealth Black",
      "variant_name": "Classic Stealth Black",
      "price": "N/A",
      "engine_displacement": "N/A cc",
      "mileage": "N/A kmpl",
      "max_power": "N/A bhp",
      "max_torque": "N/A",
      "top_speed": "N/A kmph",
      "fuel_type": "Petrol",
      "source_section": "Available",
      "description": "The Royal Enfield Classic Stealth Black is a two-wheeler available in India.",
      "features": [],
      "variants": [
        {
          "name": "Standard",
          "price": "N/A"
        },
        {
          "name": "ABS",
          "price": "N/A"
        }
      ],
      "colors": [],
      "technical_specifications": {}
    },
    {
      "make": "Royal Enfield",
      "model": "Classic 500",
      "variant_name": "Classic 500",
      "price": "N/A",
      "engine_displacement": "N/A cc",
      "mileage": "N/A kmpl",
      "max_power": "N/A bhp",
      "max_torque": "N/A",
      "top_speed": "N/A kmph",
      "fuel_type": "Petrol",
      "source_section": "Available",
      "description": "The Royal Enfield Classic 500 is a two-wheeler available in India.",
      "features": [],
      "variants": [
        {
          "name": "Desert Storm",
          "price": "N/A"
        },
        {
          "name": "Chrome",
          "price": "N/A"
        },
        {
          "name": "Single Disc",
          "price": "N/A"
        },
        {
          "name": "Dual Disc",
          "price": "N/A"
        },
        {
          "name": "ABS",
          "price": "N/A"
        }
      ],
      "colors": [],
      "technical_specifications": {}
    },
    {
      "make": "Royal Enfield",
      "model": "Thunderbird 350X",
      "variant_name": "Thunderbird 350X",
      "price": "N/A",
      "engine_displacement": "N/A cc",
      "mileage": "N/A kmpl",
      "max_power": "N/A bhp",
      "max_torque": "N/A",
      "top_speed": "N/A kmph",
      "fuel_type": "Petrol",
      "source_section": "Available",
      "description": "The Royal Enfield Thunderbird 350X is a two-wheeler available in India.",
      "features": [],
      "variants": [
        {
          "name": "Standard",
          "price": "N/A"
        },
        {
          "name": "ABS",
          "price": "N/A"
        }
      ],
      "colors": [],
      "technical_specifications": {}
    },
    {
      "make": "Royal Enfield",
      "model": "Bullet 350 [2012-2023]",
      "variant_name": "Bullet 350 [2012-2023]",
      "price": "N/A",
      "engine_displacement": "N/A cc",
      "mileage": "N/A kmpl",
      "max_power": "N/A bhp",
      "max_torque": "N/A",
      "top_speed": "N/A kmph",
      "fuel_type": "Petrol",
      "source_section": "Available",
      "description": "The Royal Enfield Bullet 350 [2012-2023] is a two-wheeler available in India.",
      "features": [],
      "variants": [
        {
          "name": "Twinspark",
          "price": "N/A"
        },
        {
          "name": "Electra Twinspark",
          "price": "N/A"
        },
        {
          "name": "Twinspark Double Disc",
          "price": "N/A"
        },
        {
          "name": "Electra Twinspark Double Disc",
          "price": "N/A"
        },
        {
          "name": "KS - ABS BS IV",
          "price": "N/A"
        },
        {
          "name": "ES - ABS BS IV",
          "price": "N/A"
        },
        {
          "name": "ES - ABS (New Colour Edition)",
          "price": "N/A"
        },
        {
          "name": "KS - ABS (New Colour Edition) ",
          "price": "N/A"
        },
        {
          "name": "Standard",
          "price": "N/A"
        },
        {
          "name": "KS",
          "price": "N/A"
        },
        {
          "name": "ES",
          "price": "N/A"
        }
      ],
      "colors": [],
      "technical_specifications": {}
    },
    {
      "make": "Royal Enfield",
      "model": "Classic 350 [2020]",
      "variant_name": "Classic 350 [2020]",
      "price": "N/A",
      "engine_displacement": "N/A cc",
      "mileage": "N/A kmpl",
      "max_power": "N/A bhp",
      "max_torque": "N/A",
      "top_speed": "N/A kmph",
      "fuel_type": "Petrol",
      "source_section": "Available",
      "description": "The Royal Enfield Classic 350 [2020] is a two-wheeler available in India.",
      "features": [],
      "variants": [
        {
          "name": "Standard",
          "price": "N/A"
        },
        {
          "name": "Redditch Edition - Single Disc",
          "price": "N/A"
        },
        {
          "name": "Redditch Edition - Dual Disc",
          "price": "N/A"
        },
        {
          "name": "Redditch Ed- Dual Channel ABS",
          "price": "N/A"
        },
        {
          "name": "Standard - Dual Channel ABS",
          "price": "N/A"
        },
        {
          "name": "Single Channel ABS",
          "price": "N/A"
        },
        {
          "name": "Standard - BS VI",
          "price": "N/A"
        },
        {
          "name": "Gun Metal Grey - BS VI (Spoke)",
          "price": "N/A"
        },
        {
          "name": "Chrome and Stealth - BS VI",
          "price": "N/A"
        },
        {
          "name": "Sandstone and Airborne - BS VI",
          "price": "N/A"
        },
        {
          "name": "Single Channel ABS - BS VI",
          "price": "N/A"
        },
        {
          "name": "Gun Metal Grey - BS VI (Alloy)",
          "price": "N/A"
        },
        {
          "name": "Orange Ember & Metallo Silver",
          "price": "N/A"
        }
      ],
      "colors": [],
      "technical_specifications": {}
    },
    {
      "make": "Royal Enfield",
      "model": "Bullet 500",
      "variant_name": "Bullet 500",
      "price": "N/A",
      "engine_displacement": "N/A cc",
      "mileage": "N/A kmpl",
      "max_power": "N/A bhp",
      "max_torque": "N/A",
      "top_speed": "N/A kmph",
      "fuel_type": "Petrol",
      "source_section": "Available",
      "description": "The Royal Enfield Bullet 500 is a two-wheeler available in India.",
      "features": [],
      "variants": [
        {
          "name": "Rear Drum",
          "price": "N/A"
        },
        {
          "name": "Rear Disc",
          "price": "N/A"
        },
        {
          "name": "ABS",
          "price": "N/A"
        }
      ],
      "colors": [],
      "technical_specifications": {}
    },
    {
      "make": "Royal Enfield",
      "model": "Hunter 350 [2024]",
      "variant_name": "Hunter 350 [2024]",
      "price": "N/A",
      "engine_displacement": "N/A cc",
      "mileage": "N/A kmpl",
      "max_power": "N/A bhp",
      "max_torque": "N/A",
      "top_speed": "N/A kmph",
      "fuel_type": "Petrol",
      "source_section": "Available",
      "description": "The Royal Enfield Hunter 350 [2024] is a two-wheeler available in India.",
      "features": [],
      "variants": [
        {
          "name": "Metro Dapper",
          "price": "N/A"
        },
        {
          "name": "Retro Factory",
          "price": "N/A"
        },
        {
          "name": "Metro Rebel",
          "price": "N/A"
        }
      ],
      "colors": [],
      "technical_specifications": {}
    },
    {
      "make": "Royal Enfield",
      "model": "Electra [1995-1997]",
      "variant_name": "Electra [1995-1997]",
      "price": "N/A",
      "engine_displacement": "N/A cc",
      "mileage": "N/A kmpl",
      "max_power": "N/A bhp",
      "max_torque": "N/A",
      "top_speed": "N/A kmph",
      "fuel_type": "Petrol",
      "source_section": "Available",
      "description": "The Royal Enfield Electra [1995-1997] is a two-wheeler available in India.",
      "features": [],
      "variants": [
        {
          "name": "Standard",
          "price": "N/A"
        },
        {
          "name": "5s",
          "price": "N/A"
        },
        {
          "name": "Disc",
          "price": "N/A"
        }
      ],
      "colors": [],
      "technical_specifications": {}
    },
    {
      "make": "Royal Enfield",
      "model": "Machismo",
      "variant_name": "Machismo",
      "price": "N/A",
      "engine_displacement": "N/A cc",
      "mileage": "N/A kmpl",
      "max_power": "N/A bhp",
      "max_torque": "N/A",
      "top_speed": "N/A kmph",
      "fuel_type": "Petrol",
      "source_section": "Available",
      "description": "The Royal Enfield Machismo is a two-wheeler available in India.",
      "features": [],
      "variants": [
        {
          "name": "350",
          "price": "N/A"
        },
        {
          "name": "500",
          "price": "N/A"
        }
      ],
      "colors": [],
      "technical_specifications": {}
    },
    {
      "make": "Royal Enfield",
      "model": "Thunderbird Twinspark",
      "variant_name": "Thunderbird Twinspark",
      "price": "N/A",
      "engine_displacement": "N/A cc",
      "mileage": "N/A kmpl",
      "max_power": "N/A bhp",
      "max_torque": "N/A",
      "top_speed": "N/A kmph",
      "fuel_type": "Petrol",
      "source_section": "Available",
      "description": "The Royal Enfield Thunderbird Twinspark is a two-wheeler available in India.",
      "features": [],
      "variants": [
        {
          "name": "Standard",
          "price": "N/A"
        }
      ],
      "colors": [],
      "technical_specifications": {}
    },
    {
      "make": "Royal Enfield",
      "model": "Old Generation Classic 350 2021",
      "variant_name": "Old Generation Classic 350 2021",
      "price": "N/A",
      "engine_displacement": "N/A cc",
      "mileage": "N/A kmpl",
      "max_power": "N/A bhp",
      "max_torque": "N/A",
      "top_speed": "N/A kmph",
      "fuel_type": "Petrol",
      "source_section": "Available",
      "description": "The Royal Enfield Old Generation Classic 350 2021 is a two-wheeler available in India.",
      "features": [],
      "variants": [
        {
          "name": "Halcyon - Dual Channel ABS",
          "price": "N/A"
        },
        {
          "name": "Redditch - Single Channel ABS",
          "price": "N/A"
        },
        {
          "name": "Classic Chrome - Dual Channel ABS",
          "price": "N/A"
        },
        {
          "name": "Classic Dark - Dual Channel ABS",
          "price": "N/A"
        },
        {
          "name": "Classic Signals - Dual Channel ABS",
          "price": "N/A"
        },
        {
          "name": "Halcyon - Single Channel ABS",
          "price": "N/A"
        }
      ],
      "colors": [],
      "technical_specifications": {}
    },
    {
      "make": "Royal Enfield",
      "model": "Thunderbird 500",
      "variant_name": "Thunderbird 500",
      "price": "N/A",
      "engine_displacement": "N/A cc",
      "mileage": "N/A kmpl",
      "max_power": "N/A bhp",
      "max_torque": "N/A",
      "top_speed": "N/A kmph",
      "fuel_type": "Petrol",
      "source_section": "Available",
      "description": "The Royal Enfield Thunderbird 500 is a two-wheeler available in India.",
      "features": [],
      "variants": [
        {
          "name": "Standard",
          "price": "N/A"
        },
        {
          "name": "ABS",
          "price": "N/A"
        }
      ],
      "colors": [],
      "technical_specifications": {}
    },
    {
      "make": "Royal Enfield",
      "model": "Bullet Trials 500",
      "variant_name": "Bullet Trials 500",
      "price": "N/A",
      "engine_displacement": "N/A cc",
      "mileage": "N/A kmpl",
      "max_power": "N/A bhp",
      "max_torque": "N/A",
      "top_speed": "N/A kmph",
      "fuel_type": "Petrol",
      "source_section": "Available",
      "description": "The Royal Enfield Bullet Trials 500 is a two-wheeler available in India.",
      "features": [],
      "variants": [
        {
          "name": "Dual Channel ABS",
          "price": "N/A"
        }
      ],
      "colors": [],
      "technical_specifications": {}
    },
    {
      "make": "Royal Enfield",
      "model": "Bullet Trials 350",
      "variant_name": "Bullet Trials 350",
      "price": "N/A",
      "engine_displacement": "N/A cc",
      "mileage": "N/A kmpl",
      "max_power": "N/A bhp",
      "max_torque": "N/A",
      "top_speed": "N/A kmph",
      "fuel_type": "Petrol",
      "source_section": "Available",
      "description": "The Royal Enfield Bullet Trials 350 is a two-wheeler available in India.",
      "features": [],
      "variants": [
        {
          "name": "Dual Channel ABS",
          "price": "N/A"
        }
      ],
      "colors": [],
      "technical_specifications": {}
    },
    {
      "make": "Royal Enfield",
      "model": "Classic 500 Pegasus",
      "variant_name": "Classic 500 Pegasus",
      "price": "N/A",
      "engine_displacement": "N/A cc",
      "mileage": "N/A kmpl",
      "max_power": "N/A bhp",
      "max_torque": "N/A",
      "top_speed": "N/A kmph",
      "fuel_type": "Petrol",
      "source_section": "Available",
      "description": "The Royal Enfield Classic 500 Pegasus is a two-wheeler available in India.",
      "features": [],
      "variants": [
        {
          "name": "Standard",
          "price": "N/A"
        }
      ],
      "colors": [],
      "technical_specifications": {}
    },
    {
      "make": "Royal Enfield",
      "model": "Thunderbird 500X",
      "variant_name": "Thunderbird 500X",
      "price": "N/A",
      "engine_displacement": "N/A cc",
      "mileage": "N/A kmpl",
      "max_power": "N/A bhp",
      "max_torque": "N/A",
      "top_speed": "N/A kmph",
      "fuel_type": "Petrol",
      "source_section": "Available",
      "description": "The Royal Enfield Thunderbird 500X is a two-wheeler available in India.",
      "features": [],
      "variants": [
        {
          "name": "Standard",
          "price": "N/A"
        },
        {
          "name": "ABS",
          "price": "N/A"
        }
      ],
      "colors": [],
      "technical_specifications": {}
    },
    {
      "make": "Royal Enfield",
      "model": "Continental GT [2013 - 2018]",
      "variant_name": "Continental GT [2013 - 2018]",
      "price": "N/A",
      "engine_displacement": "N/A cc",
      "mileage": "N/A kmpl",
      "max_power": "N/A bhp",
      "max_torque": "N/A",
      "top_speed": "N/A kmph",
      "fuel_type": "Petrol",
      "source_section": "Available",
      "description": "The Royal Enfield Continental GT [2013 - 2018] is a two-wheeler available in India.",
      "features": [],
      "variants": [
        {
          "name": "Standard",
          "price": "N/A"
        }
      ],
      "colors": [],
      "technical_specifications": {}
    },
    {
      "make": "Royal Enfield",
      "model": "Lightning",
      "variant_name": "Lightning",
      "price": "N/A",
      "engine_displacement": "N/A cc",
      "mileage": "N/A kmpl",
      "max_power": "N/A bhp",
      "max_torque": "N/A",
      "top_speed": "N/A kmph",
      "fuel_type": "Petrol",
      "source_section": "Available",
      "description": "The Royal Enfield Lightning is a two-wheeler available in India.",
      "features": [],
      "variants": [
        {
          "name": "Standard",
          "price": "N/A"
        }
      ],
      "colors": [],
      "technical_specifications": {}
    },
    {
      "make": "Royal Enfield",
      "model": "Classic Gunmetal Grey",
      "variant_name": "Classic Gunmetal Grey",
      "price": "N/A",
      "engine_displacement": "N/A cc",
      "mileage": "N/A kmpl",
      "max_power": "N/A bhp",
      "max_torque": "N/A",
      "top_speed": "N/A kmph",
      "fuel_type": "Petrol",
      "source_section": "Available",
      "description": "The Royal Enfield Classic Gunmetal Grey is a two-wheeler available in India.",
      "features": [],
      "variants": [
        {
          "name": "Standard",
          "price": "N/A"
        },
        {
          "name": "Redditch Edition",
          "price": "N/A"
        },
        {
          "name": "ABS",
          "price": "N/A"
        }
      ],
      "colors": [],
      "technical_specifications": {}
    },
    {
      "make": "Royal Enfield",
      "model": "Classic Squadron Blue",
      "variant_name": "Classic Squadron Blue",
      "price": "N/A",
      "engine_displacement": "N/A cc",
      "mileage": "N/A kmpl",
      "max_power": "N/A bhp",
      "max_torque": "N/A",
      "top_speed": "N/A kmph",
      "fuel_type": "Petrol",
      "source_section": "Available",
      "description": "The Royal Enfield Classic Squadron Blue is a two-wheeler available in India.",
      "features": [],
      "variants": [
        {
          "name": "Single Disc",
          "price": "N/A"
        },
        {
          "name": "Dual Disc",
          "price": "N/A"
        },
        {
          "name": "ABS",
          "price": "N/A"
        }
      ],
      "colors": [],
      "technical_specifications": {}
    },
    {
      "make": "Royal Enfield",
      "model": "Crusader",
      "variant_name": "Crusader",
      "price": "N/A",
      "engine_displacement": "N/A cc",
      "mileage": "N/A kmpl",
      "max_power": "N/A bhp",
      "max_torque": "N/A",
      "top_speed": "N/A kmph",
      "fuel_type": "Petrol",
      "source_section": "Available",
      "description": "The Royal Enfield Crusader is a two-wheeler available in India.",
      "features": [],
      "variants": [
        {
          "name": "Standard",
          "price": "N/A"
        }
      ],
      "colors": [],
      "technical_specifications": {}
    },
    {
      "make": "Royal Enfield",
      "model": "Electra Twinspark",
      "variant_name": "Electra Twinspark",
      "price": "N/A",
      "engine_displacement": "N/A cc",
      "mileage": "N/A kmpl",
      "max_power": "N/A bhp",
      "max_torque": "N/A",
      "top_speed": "N/A kmph",
      "fuel_type": "Petrol",
      "source_section": "Available",
      "description": "The Royal Enfield Electra Twinspark is a two-wheeler available in India.",
      "features": [],
      "variants": [
        {
          "name": "Standard",
          "price": "N/A"
        }
      ],
      "colors": [],
      "technical_specifications": {}
    },
    {
      "make": "Royal Enfield",
      "model": "Electra 5 S",
      "variant_name": "Electra 5 S",
      "price": "N/A",
      "engine_displacement": "N/A cc",
      "mileage": "N/A kmpl",
      "max_power": "N/A bhp",
      "max_torque": "N/A",
      "top_speed": "N/A kmph",
      "fuel_type": "Petrol",
      "source_section": "Available",
      "description": "The Royal Enfield Electra 5 S is a two-wheeler available in India.",
      "features": [],
      "variants": [
        {
          "name": "Disc Kick",
          "price": "N/A"
        },
        {
          "name": "Disc Self",
          "price": "N/A"
        },
        {
          "name": "Drum Kick",
          "price": "N/A"
        },
        {
          "name": "Drum Self",
          "price": "N/A"
        }
      ],
      "colors": [],
      "technical_specifications": {}
    },
    {
      "make": "Royal Enfield",
      "model": "Electra 4 S",
      "variant_name": "Electra 4 S",
      "price": "N/A",
      "engine_displacement": "N/A cc",
      "mileage": "N/A kmpl",
      "max_power": "N/A bhp",
      "max_torque": "N/A",
      "top_speed": "N/A kmph",
      "fuel_type": "Petrol",
      "source_section": "Available",
      "description": "The Royal Enfield Electra 4 S is a two-wheeler available in India.",
      "features": [],
      "variants": [
        {
          "name": "Kick",
          "price": "N/A"
        },
        {
          "name": "Self",
          "price": "N/A"
        }
      ],
      "colors": [],
      "technical_specifications": {}
    },
    {
      "make": "Royal Enfield",
      "model": "Bullet 350 [2007-2011]",
      "variant_name": "Bullet 350 [2007-2011]",
      "price": "N/A",
      "engine_displacement": "N/A cc",
      "mileage": "N/A kmpl",
      "max_power": "N/A bhp",
      "max_torque": "N/A",
      "top_speed": "N/A kmph",
      "fuel_type": "Petrol",
      "source_section": "Available",
      "description": "The Royal Enfield Bullet 350 [2007-2011] is a two-wheeler available in India.",
      "features": [],
      "variants": [
        {
          "name": "Standard",
          "price": "N/A"
        }
      ],
      "colors": [],
      "technical_specifications": {}
    },
    {
      "make": "Royal Enfield",
      "model": "Classic Chrome",
      "variant_name": "Classic Chrome",
      "price": "N/A",
      "engine_displacement": "N/A cc",
      "mileage": "N/A kmpl",
      "max_power": "N/A bhp",
      "max_torque": "N/A",
      "top_speed": "N/A kmph",
      "fuel_type": "Petrol",
      "source_section": "Available",
      "description": "The Royal Enfield Classic Chrome is a two-wheeler available in India.",
      "features": [],
      "variants": [
        {
          "name": "Single Disc",
          "price": "N/A"
        },
        {
          "name": "Dual Disc",
          "price": "N/A"
        },
        {
          "name": "ABS",
          "price": "N/A"
        }
      ],
      "colors": [],
      "technical_specifications": {}
    },
    {
      "make": "Royal Enfield",
      "model": "Classic Desert Storm",
      "variant_name": "Classic Desert Storm",
      "price": "N/A",
      "engine_displacement": "N/A cc",
      "mileage": "N/A kmpl",
      "max_power": "N/A bhp",
      "max_torque": "N/A",
      "top_speed": "N/A kmph",
      "fuel_type": "Petrol",
      "source_section": "Available",
      "description": "The Royal Enfield Classic Desert Storm is a two-wheeler available in India.",
      "features": [],
      "variants": [
        {
          "name": "Single Disc",
          "price": "N/A"
        },
        {
          "name": "Dual Disc",
          "price": "N/A"
        },
        {
          "name": "ABS",
          "price": "N/A"
        }
      ],
      "colors": [],
      "technical_specifications": {}
    },
    {
      "make": "Royal Enfield",
      "model": "Superstar",
      "variant_name": "Superstar",
      "price": "N/A",
      "engine_displacement": "N/A cc",
      "mileage": "N/A kmpl",
      "max_power": "N/A bhp",
      "max_torque": "N/A",
      "top_speed": "N/A kmph",
      "fuel_type": "Petrol",
      "source_section": "Available",
      "description": "The Royal Enfield Superstar is a two-wheeler available in India.",
      "features": [],
      "variants": [
        {
          "name": "Standard",
          "price": "N/A"
        }
      ],
      "colors": [],
      "technical_specifications": {}
    },
    {
      "make": "Royal Enfield",
      "model": "Mini Bullet",
      "variant_name": "Mini Bullet",
      "price": "N/A",
      "engine_displacement": "N/A cc",
      "mileage": "N/A kmpl",
      "max_power": "N/A bhp",
      "max_torque": "N/A",
      "top_speed": "N/A kmph",
      "fuel_type": "Petrol",
      "source_section": "Available",
      "description": "The Royal Enfield Mini Bullet is a two-wheeler available in India.",
      "features": [],
      "variants": [
        {
          "name": "Standard",
          "price": "N/A"
        }
      ],
      "colors": [],
      "technical_specifications": {}
    }
  ]
}