{
  "brand": "Yo",
  "brandId": "yo",
  "type": "2w",
  "lastUpdated": "2026-04-03",
  "source": "BikeWale",
  "vehicles": [
    {
      "make": "Yo",
      "model": "Edge",
      "variant_name": "YO Edge",
      "price": "₹67,484",
      "engine_displacement": "N/A",
      "mileage": "60 km (range)",
      "max_power": "250 W",
      "max_torque": "12 Nm",
      "top_speed": "25 kmph",
      "fuel_type": "Electric",
      "transmission": "Automatic",
      "source_section": "Available",
      "description": "The YO Edge is an affordable low-speed electric scooter with 60km range, 25 kmph top speed, lightweight 59kg design, and 7-8 hour charging. Available across 90 Indian cities. Rated 4.1/5 by owners.",
      "features": ["LED Headlamp", "Digital Speedometer", "Lightweight Design"],
      "variants": [{"name": "Edge Standard", "price": "₹67,484"}],
      "colors": [
        {"name": "Red", "hex": "#C41E3A"},
        {"name": "Blue", "hex": "#1A4A8B"},
        {"name": "White", "hex": "#F5F5F0"},
        {"name": "Black", "hex": "#1A1A1A"}
      ],
      "technical_specifications": {
        "motor": "BLDC Motor",
        "motor_power": "250 W",
        "battery": "N/A",
        "range": "60 km",
        "charging_time": "7-8 hrs",
        "top_speed": "25 kmph",
        "brakes_front": "Drum",
        "brakes_rear": "Drum",
        "kerb_weight": "59 kg",
        "seat_height": "N/A"
      }
    },
    {
      "make": "Yo",
      "model": "Drift",
      "variant_name": "YO Drift",
      "price": "₹71,283",
      "engine_displacement": "N/A",
      "mileage": "60 km (range)",
      "max_power": "250 W",
      "max_torque": "12 Nm",
      "top_speed": "25 kmph",
      "fuel_type": "Electric",
      "transmission": "Automatic",
      "source_section": "Available",
      "description": "The YO Drift is the premium variant of YO scooters with 60km range, 25 kmph top speed, and sporty styling. Slightly higher price than the Edge.",
      "features": ["LED Headlamp", "Digital Speedometer", "Sporty Design"],
      "variants": [{"name": "Drift Standard", "price": "₹71,283"}],
      "colors": [
        {"name": "Red", "hex": "#C41E3A"},
        {"name": "Blue", "hex": "#1A4A8B"},
        {"name": "White", "hex": "#F5F5F0"},
        {"name": "Black", "hex": "#1A1A1A"},
        {"name": "Green", "hex": "#4CAF50"}
      ],
      "technical_specifications": {
        "motor": "BLDC Motor",
        "motor_power": "250 W",
        "battery": "N/A",
        "range": "60 km",
        "charging_time": "7-8 hrs",
        "top_speed": "25 kmph",
        "brakes_front": "Drum",
        "brakes_rear": "Drum",
        "kerb_weight": "59 kg",
        "seat_height": "N/A"
      }
    },
    {
      "make": "Yo",
      "model": "EXL",
      "variant_name": "YO EXL",
      "price": "N/A",
      "engine_displacement": "N/A",
      "mileage": "N/A",
      "max_power": "1.5 kW",
      "max_torque": "45 Nm",
      "top_speed": "N/A",
      "fuel_type": "Electric",
      "transmission": "Automatic",
      "source_section": "Discontinued",
      "description": "The YO EXL was a discontinued electric scooter from YO! Bykes.",
      "features": [],
      "variants": [],
      "colors": [],
      "technical_specifications": {}
    },
    {
      "make": "Yo",
      "model": "Xplor",
      "variant_name": "YO Xplor",
      "price": "N/A",
      "engine_displacement": "N/A",
      "mileage": "N/A",
      "max_power": "2 kW",
      "max_torque": "60 Nm",
      "top_speed": "N/A",
      "fuel_type": "Electric",
      "transmission": "Automatic",
      "source_section": "Discontinued",
      "description": "The YO Xplor was a discontinued electric scooter from YO! Bykes.",
      "features": [],
      "variants": [],
      "colors": [],
      "technical_specifications": {}
    }
  ]
}
