{
  "brand": "Mahindra (3W)",
  "brandId": "mahindra-3w",
  "type": "3w",
  "vehicles": [
    {
      "make": "Mahindra (3W)",
      "model": "Alfa Passenger",
      "category": "passenger",
      "fuel_type": "CNG",
      "engine_cc": 435,
      "mileage_km_per_kg": 30,
      "max_power": "9.7 bhp",
      "torque": "24 Nm",
      "max_speed_kmph": 55,
      "passenger_capacity": 3,
      "gvw_kg": 980,
      "ex_showroom_price": "₹2.80 Lakh",
      "status": "Available",
      "variants": []
    },
    {
      "make": "Mahindra (3W)",
      "model": "E-Alfa Plus",
      "category": "passenger",
      "fuel_type": "Electric",
      "range_km": 120,
      "max_power": "8 kW",
      "max_speed_kmph": 45,
      "battery_kwh": 7.37,
      "charging_time_hours": 6,
      "passenger_capacity": 3,
      "gvw_kg": 960,
      "ex_showroom_price": "₹3.60 Lakh",
      "status": "Available",
      "variants": []
    },
    {
      "make": "Mahindra (3W)",
      "model": "E-Alfa Mini",
      "category": "passenger",
      "fuel_type": "Electric",
      "range_km": 80,
      "max_power": "5.4 kW",
      "max_speed_kmph": 40,
      "battery_kwh": 4.8,
      "charging_time_hours": 4,
      "passenger_capacity": 3,
      "gvw_kg": 880,
      "ex_showroom_price": "₹2.90 Lakh",
      "status": "Available",
      "variants": []
    },
    {
      "make": "Mahindra (3W)",
      "model": "Alfa Load",
      "category": "cargo",
      "fuel_type": "CNG",
      "engine_cc": 435,
      "mileage_km_per_kg": 28,
      "max_power": "9.7 bhp",
      "torque": "24 Nm",
      "max_speed_kmph": 50,
      "payload_kg": 580,
      "gvw_kg": 1120,
      "ex_showroom_price": "₹3.00 Lakh",
      "status": "Available",
      "variants": []
    },
    {
      "make": "Mahindra (3W)",
      "model": "Zor Grand",
      "category": "cargo",
      "fuel_type": "CNG",
      "engine_cc": 435,
      "mileage_km_per_kg": 27,
      "max_power": "11 bhp",
      "torque": "28 Nm",
      "max_speed_kmph": 55,
      "payload_kg": 700,
      "gvw_kg": 1250,
      "ex_showroom_price": "₹3.50 Lakh",
      "status": "Available",
      "variants": []
    },
    {
      "make": "Mahindra (3W)",
      "model": "Treo",
      "category": "electric",
      "fuel_type": "Electric",
      "range_km": 130,
      "max_power": "8 kW",
      "max_speed_kmph": 45,
      "battery_kwh": 7.37,
      "charging_time_hours": 6,
      "passenger_capacity": 3,
      "gvw_kg": 960,
      "ex_showroom_price": "₹3.80 Lakh",
      "status": "Available",
      "variants": []
    },
    {
      "make": "Mahindra (3W)",
      "model": "Treo Plus",
      "category": "electric",
      "fuel_type": "Electric",
      "range_km": 130,
      "max_power": "8 kW",
      "max_speed_kmph": 45,
      "battery_kwh": 9.67,
      "charging_time_hours": 7,
      "passenger_capacity": 3,
      "gvw_kg": 980,
      "ex_showroom_price": "₹4.10 Lakh",
      "status": "Available",
      "variants": []
    },
    {
      "make": "Mahindra (3W)",
      "model": "Treo Zor",
      "category": "electric",
      "fuel_type": "Electric",
      "range_km": 150,
      "max_power": "8 kW",
      "max_speed_kmph": 45,
      "battery_kwh": 9.67,
      "charging_time_hours": 7,
      "payload_kg": 550,
      "gvw_kg": 1100,
      "ex_showroom_price": "₹4.30 Lakh",
      "status": "Available",
      "variants": []
    },
    {
      "make": "Mahindra (3W)",
      "model": "Treo Yaari HRT",
      "category": "electric",
      "fuel_type": "Electric",
      "range_km": 130,
      "max_power": "8 kW",
      "max_speed_kmph": 45,
      "battery_kwh": 7.37,
      "charging_time_hours": 6,
      "passenger_capacity": 3,
      "gvw_kg": 960,
      "ex_showroom_price": "₹4.50 Lakh",
      "status": "Available",
      "variants": []
    },
    {
      "make": "Mahindra (3W)",
      "model": "Treo Yaari SFT",
      "category": "electric",
      "fuel_type": "Electric",
      "range_km": 130,
      "max_power": "8 kW",
      "max_speed_kmph": 45,
      "battery_kwh": 7.37,
      "charging_time_hours": 6,
      "passenger_capacity": 3,
      "gvw_kg": 960,
      "ex_showroom_price": "₹4.70 Lakh",
      "status": "Available",
      "variants": []
    },
    {
      "make": "Mahindra (3W)",
      "model": "UDO",
      "category": "electric",
      "fuel_type": "Electric",
      "range_km": 125,
      "max_power": "11 kW",
      "max_speed_kmph": 50,
      "battery_kwh": 11.6,
      "charging_time_hours": 8,
      "payload_kg": 600,
      "gvw_kg": 1200,
      "ex_showroom_price": "₹5.50 Lakh",
      "status": "Available",
      "variants": []
    }
  ]
}
